odoo/addons/mail_tracking/README.rst
odoo/addons/mail_tracking/__init__.py
odoo/addons/mail_tracking/__manifest__.py
odoo/addons/mail_tracking/controllers/__init__.py
odoo/addons/mail_tracking/controllers/main.py
odoo/addons/mail_tracking/data/tracking_data.xml
odoo/addons/mail_tracking/demo/demo.xml
odoo/addons/mail_tracking/i18n/am.po
odoo/addons/mail_tracking/i18n/ar.po
odoo/addons/mail_tracking/i18n/bg.po
odoo/addons/mail_tracking/i18n/bs.po
odoo/addons/mail_tracking/i18n/ca.po
odoo/addons/mail_tracking/i18n/cs.po
odoo/addons/mail_tracking/i18n/da.po
odoo/addons/mail_tracking/i18n/de.po
odoo/addons/mail_tracking/i18n/el_GR.po
odoo/addons/mail_tracking/i18n/en_GB.po
odoo/addons/mail_tracking/i18n/es.po
odoo/addons/mail_tracking/i18n/es_AR.po
odoo/addons/mail_tracking/i18n/es_CL.po
odoo/addons/mail_tracking/i18n/es_CO.po
odoo/addons/mail_tracking/i18n/es_CR.po
odoo/addons/mail_tracking/i18n/es_DO.po
odoo/addons/mail_tracking/i18n/es_EC.po
odoo/addons/mail_tracking/i18n/es_ES.po
odoo/addons/mail_tracking/i18n/es_MX.po
odoo/addons/mail_tracking/i18n/es_PE.po
odoo/addons/mail_tracking/i18n/es_PY.po
odoo/addons/mail_tracking/i18n/es_VE.po
odoo/addons/mail_tracking/i18n/et.po
odoo/addons/mail_tracking/i18n/eu.po
odoo/addons/mail_tracking/i18n/fa.po
odoo/addons/mail_tracking/i18n/fi.po
odoo/addons/mail_tracking/i18n/fr.po
odoo/addons/mail_tracking/i18n/fr_CA.po
odoo/addons/mail_tracking/i18n/fr_CH.po
odoo/addons/mail_tracking/i18n/fr_FR.po
odoo/addons/mail_tracking/i18n/gl.po
odoo/addons/mail_tracking/i18n/gl_ES.po
odoo/addons/mail_tracking/i18n/he.po
odoo/addons/mail_tracking/i18n/hr.po
odoo/addons/mail_tracking/i18n/hr_HR.po
odoo/addons/mail_tracking/i18n/hu.po
odoo/addons/mail_tracking/i18n/id.po
odoo/addons/mail_tracking/i18n/it.po
odoo/addons/mail_tracking/i18n/ja.po
odoo/addons/mail_tracking/i18n/ko.po
odoo/addons/mail_tracking/i18n/lt.po
odoo/addons/mail_tracking/i18n/lt_LT.po
odoo/addons/mail_tracking/i18n/lv.po
odoo/addons/mail_tracking/i18n/mail_tracking.pot
odoo14_addon_mail_tracking-14.0.3.2.0.dist-info/METADATA
odoo14_addon_mail_tracking-14.0.3.2.0.dist-info/WHEEL
odoo14_addon_mail_tracking-14.0.3.2.0.dist-info/top_level.txt
odoo14_addon_mail_tracking-14.0.3.2.0.dist-info/RECORD
